{
  "calculation_ready": false,
  "candidate_ledger_payload_sha256": "e774d97586b72adbc19a44825bb4ca06a11e9b5df32d48c0d0b76a193c321fc1",
  "candidates": [
    {
      "authors": [
        "Jiji Zhang",
        "Kálmán J. Szabó",
        "Fahmi Himo"
      ],
      "candidate_id": "lit-0001",
      "cited_by_count": 62,
      "deduplication_key": "doi:10.1021/acscatal.6b02731",
      "directness": "not_reviewed",
      "discovery_observations": [
        {
          "lane": "seed_doi",
          "query_id": "q024",
          "raw_sha256": "a8a1b8ad0777797ee3a57a2024634cf993179d93250fd93ca41d3e222f07860e",
          "source": "openalex"
        }
      ],
      "doi": "10.1021/acscatal.6b02731",
      "lexical_score": 11,
      "metadata_abstract_available": true,
      "publication_type": "article",
      "record_status_signals": {
        "crossref_relation_present": null,
        "crossref_update_to_present": null,
        "openalex_is_retracted": false
      },
      "score_breakdown": {
        "matched_terms": {
          "catalyst_terms": [],
          "evidence_abstract": [
            "mechanism",
            "density functional",
            "selectivity"
          ],
          "evidence_title": [
            "mechanism"
          ],
          "exact_phrases": [],
          "exclusions": [],
          "mechanism_terms": [],
          "substrate_terms": [
            "alkene"
          ],
          "transformation_terms": [
            "metathesis"
          ]
        },
        "points": {
          "catalyst_terms": 0,
          "evidence_abstract": 3,
          "evidence_title": 3,
          "exact_phrases": 0,
          "exclusions": 0,
          "mechanism_terms": 0,
          "substrate_terms": 2,
          "transformation_terms": 3
        }
      },
      "screening_status": "metadata_only_unverified",
      "screening_tier": "system_relevant_requires_full_text",
      "title": "Metathesis Mechanism of Zinc-Catalyzed Fluorination of Alkenes with Hypervalent Fluoroiodine",
      "url": "https://doi.org/10.1021/acscatal.6b02731",
      "venue": "ACS Catalysis",
      "year": 2016
    },
    {
      "authors": [
        "Mark A. Iron",
        "Trevor Janes"
      ],
      "candidate_id": "lit-0002",
      "cited_by_count": 200,
      "deduplication_key": "doi:10.1021/acs.jpca.9b01546",
      "directness": "not_reviewed",
      "discovery_observations": [
        {
          "lane": "seed_doi",
          "query_id": "q021",
          "raw_sha256": "29d7a96eebdd6e813a43c0dd119e4156a859f176382191237875d550cf1a4a67",
          "source": "openalex"
        }
      ],
      "doi": "10.1021/acs.jpca.9b01546",
      "lexical_score": 6,
      "metadata_abstract_available": true,
      "publication_type": "article",
      "record_status_signals": {
        "crossref_relation_present": null,
        "crossref_update_to_present": null,
        "openalex_is_retracted": false
      },
      "score_breakdown": {
        "matched_terms": {
          "catalyst_terms": [],
          "evidence_abstract": [
            "density functional",
            "dft",
            "computational"
          ],
          "evidence_title": [
            "density functional"
          ],
          "exact_phrases": [],
          "exclusions": [],
          "mechanism_terms": [],
          "substrate_terms": [],
          "transformation_terms": []
        },
        "points": {
          "catalyst_terms": 0,
          "evidence_abstract": 3,
          "evidence_title": 3,
          "exact_phrases": 0,
          "exclusions": 0,
          "mechanism_terms": 0,
          "substrate_terms": 0,
          "transformation_terms": 0
        }
      },
      "screening_status": "metadata_only_unverified",
      "screening_tier": "analogy_or_background_screen",
      "title": "Evaluating Transition Metal Barrier Heights with the Latest Density Functional Theory Exchange–Correlation Functionals: The MOBH35 Benchmark Database",
      "url": "https://doi.org/10.1021/acs.jpca.9b01546",
      "venue": "The Journal of Physical Chemistry A",
      "year": 2019
    },
    {
      "authors": [
        "Jianzhong Chen",
        "Zhenfeng Zhang",
        "Bowen Li",
        "Feilong Li",
        "Yulin Wang",
        "Min Zhao",
        "Ilya D. Gridnev",
        "Tsuneo Imamoto",
        "Wanbin Zhang"
      ],
      "candidate_id": "lit-0003",
      "cited_by_count": 99,
      "deduplication_key": "doi:10.1038/s41467-018-07462-w",
      "directness": "not_reviewed",
      "discovery_observations": [
        {
          "lane": "seed_doi",
          "query_id": "q023",
          "raw_sha256": "8d1767da47ba7c7a4a8055bf17bc055aad9ebfedfc699d25fc6396dda8397d4a",
          "source": "openalex"
        }
      ],
      "doi": "10.1038/s41467-018-07462-w",
      "lexical_score": 5,
      "metadata_abstract_available": true,
      "publication_type": "article",
      "record_status_signals": {
        "crossref_relation_present": null,
        "crossref_update_to_present": null,
        "openalex_is_retracted": false
      },
      "score_breakdown": {
        "matched_terms": {
          "catalyst_terms": [],
          "evidence_abstract": [],
          "evidence_title": [],
          "exact_phrases": [],
          "exclusions": [],
          "mechanism_terms": [],
          "substrate_terms": [
            "imine"
          ],
          "transformation_terms": [
            "asymmetric hydrogenation"
          ]
        },
        "points": {
          "catalyst_terms": 0,
          "evidence_abstract": 0,
          "evidence_title": 0,
          "exact_phrases": 0,
          "exclusions": 0,
          "mechanism_terms": 0,
          "substrate_terms": 2,
          "transformation_terms": 3
        }
      },
      "screening_status": "metadata_only_unverified",
      "screening_tier": "analogy_or_background_screen",
      "title": "Pd(OAc)2-catalyzed asymmetric hydrogenation of sterically hindered N-tosylimines",
      "url": "https://doi.org/10.1038/s41467-018-07462-w",
      "venue": "Nature Communications",
      "year": 2018
    },
    {
      "authors": [
        "Mark A. Iron",
        "Trevor Janes"
      ],
      "candidate_id": "lit-0004",
      "cited_by_count": 66,
      "deduplication_key": "doi:10.1021/acs.jpca.9b06135",
      "directness": "not_reviewed",
      "discovery_observations": [
        {
          "lane": "seed_doi",
          "query_id": "q022",
          "raw_sha256": "1aa7d3bb3f03aa9693be1e5d704dc351df0c689a3272ad22838fa80558fd48f4",
          "source": "openalex"
        }
      ],
      "doi": "10.1021/acs.jpca.9b06135",
      "lexical_score": 4,
      "metadata_abstract_available": true,
      "publication_type": "erratum",
      "record_status_signals": {
        "crossref_relation_present": null,
        "crossref_update_to_present": null,
        "openalex_is_retracted": false
      },
      "score_breakdown": {
        "matched_terms": {
          "catalyst_terms": [],
          "evidence_abstract": [
            "density functional"
          ],
          "evidence_title": [
            "density functional"
          ],
          "exact_phrases": [],
          "exclusions": [],
          "mechanism_terms": [],
          "substrate_terms": [],
          "transformation_terms": []
        },
        "points": {
          "catalyst_terms": 0,
          "evidence_abstract": 1,
          "evidence_title": 3,
          "exact_phrases": 0,
          "exclusions": 0,
          "mechanism_terms": 0,
          "substrate_terms": 0,
          "transformation_terms": 0
        }
      },
      "screening_status": "metadata_only_unverified",
      "screening_tier": "analogy_or_background_screen",
      "title": "Correction to “Evaluating Transition Metal Barrier Heights with the Latest Density Functional Theory Exchange–Correlation Functionals: The MOBH35 Benchmark Database”",
      "url": "https://doi.org/10.1021/acs.jpca.9b06135",
      "venue": "The Journal of Physical Chemistry A",
      "year": 2019
    },
    {
      "authors": [
        "Qi-Fei Liu",
        "Qianqian Peng",
        "Sheng-Shi Hao",
        "Lu Liu",
        "Fu-Hao Zhang",
        "Zhu-Jun Shi",
        "Jian‐Hua Xie",
        "Chongren Ai",
        "Xiaochen Wang"
      ],
      "candidate_id": "lit-0005",
      "cited_by_count": 3,
      "deduplication_key": "doi:10.1021/jacs.5c13835",
      "directness": "not_reviewed",
      "discovery_observations": [
        {
          "lane": "seed_doi",
          "query_id": "q025",
          "raw_sha256": "306d704698d6ce0bd8ad2e1ba0bf79b2def657b4daa1fec6fbc2801328ddfdac",
          "source": "openalex"
        }
      ],
      "doi": "10.1021/jacs.5c13835",
      "lexical_score": 0,
      "metadata_abstract_available": true,
      "publication_type": "article",
      "record_status_signals": {
        "crossref_relation_present": null,
        "crossref_update_to_present": null,
        "openalex_is_retracted": false
      },
      "score_breakdown": {
        "matched_terms": {
          "catalyst_terms": [],
          "evidence_abstract": [],
          "evidence_title": [],
          "exact_phrases": [],
          "exclusions": [],
          "mechanism_terms": [],
          "substrate_terms": [],
          "transformation_terms": []
        },
        "points": {
          "catalyst_terms": 0,
          "evidence_abstract": 0,
          "evidence_title": 0,
          "exact_phrases": 0,
          "exclusions": 0,
          "mechanism_terms": 0,
          "substrate_terms": 0,
          "transformation_terms": 0
        }
      },
      "screening_status": "metadata_only_unverified",
      "screening_tier": "low_lexical_match",
      "title": "Borane/Transition Metal–Catalyzed Allenylic and Allylic Alkylation of Unactivated 2-Alkylbenzoxazoles",
      "url": "https://doi.org/10.1021/jacs.5c13835",
      "venue": "Journal of the American Chemical Society",
      "year": 2025
    },
    {
      "authors": [
        "Emmanouil Semidalas",
        "Jan M. L. Martin"
      ],
      "candidate_id": "lit-0006",
      "cited_by_count": 63,
      "deduplication_key": "doi:10.1021/acs.jctc.1c01126",
      "directness": "not_reviewed",
      "discovery_observations": [
        {
          "lane": "seed_doi",
          "query_id": "q020",
          "raw_sha256": "cec225ba15b371be8ca434a9813e9a0bb3d735b3ac95deef97c1d1ea57d56b76",
          "source": "openalex"
        }
      ],
      "doi": "10.1021/acs.jctc.1c01126",
      "lexical_score": 0,
      "metadata_abstract_available": true,
      "publication_type": "article",
      "record_status_signals": {
        "crossref_relation_present": null,
        "crossref_update_to_present": null,
        "openalex_is_retracted": false
      },
      "score_breakdown": {
        "matched_terms": {
          "catalyst_terms": [],
          "evidence_abstract": [],
          "evidence_title": [],
          "exact_phrases": [],
          "exclusions": [],
          "mechanism_terms": [],
          "substrate_terms": [],
          "transformation_terms": []
        },
        "points": {
          "catalyst_terms": 0,
          "evidence_abstract": 0,
          "evidence_title": 0,
          "exact_phrases": 0,
          "exclusions": 0,
          "mechanism_terms": 0,
          "substrate_terms": 0,
          "transformation_terms": 0
        }
      },
      "screening_status": "metadata_only_unverified",
      "screening_tier": "low_lexical_match",
      "title": "The MOBH35 Metal–Organic Barrier Heights Reconsidered: Performance of Local-Orbital Coupled Cluster Approaches in Different Static Correlation Regimes",
      "url": "https://doi.org/10.1021/acs.jctc.1c01126",
      "venue": "Journal of Chemical Theory and Computation",
      "year": 2022
    }
  ],
  "counts": {
    "candidates_retained": 6,
    "normalized_raw_records": 6,
    "unique_candidates": 6
  },
  "created_at": "2026-07-16T10:12:47+00:00",
  "limitations": [
    "No title, abstract, snippet, API relevance score, or citation count is accepted as mechanism or TS evidence.",
    "Primary article and version-matched SI review are still required.",
    "Preprint/version-of-record relations and corrections require manual verification."
  ],
  "no_submission_authorization": true,
  "promotable_to_mechanism_support": false,
  "promotable_to_ts_precedent_map": false,
  "promotion_blockers": [
    "missing_upstream_binding:reaction_intake",
    "missing_upstream_binding:species_registry",
    "missing_upstream_binding:condition_model",
    "missing_upstream_binding:knowledge_snapshot"
  ],
  "ranking_policy": {
    "citation_count_used_in_score": false,
    "scientific_acceptance_performed": false,
    "type": "transparent_lexical_screening_only"
  },
  "request_id": "metal_m4_p0_candidate_search_20260716",
  "retrieval_artifact": {
    "path": "studies/metal_m4_p0_p1_baseline/retrieval-doi-seeds/retrieval.json",
    "sha256": "1eb8300287fc458864ad3e718d022511aa11c4c566a8e67983fbf43d33fda4aa"
  },
  "schema": "gaussian-reaction-literature-candidate-ledger/1",
  "search_plan_artifact": {
    "path": "studies/metal_m4_p0_p1_baseline/search-plan-v2.json",
    "sha256": "0ca5d1cb8cfeaa613a382944ca51784303b28c6e892972527d4f0538cbfa598e"
  },
  "target_evidence": [
    "active_catalyst_state",
    "elementary_step",
    "transition_state_model",
    "computational_protocol",
    "normal_mode",
    "irc",
    "coordinates"
  ],
  "upstream_artifacts": {
    "condition_model": null,
    "knowledge_snapshot": null,
    "reaction_intake": null,
    "species_registry": null
  },
  "w2_binding_status": "standalone_search_not_promotable"
}
